strip_ansi/__init__.py
strip_ansi-0.1.0.dist-info/WHEEL
strip_ansi-0.1.0.dist-info/METADATA
strip_ansi-0.1.0.dist-info/RECORD
