Metadata-Version: 2.1
Name: strip-ansi
Version: 0.1.0
Summary: Strip ANSI escape sequences from a string
Home-page: https://github.com/ewen-lbh/python-strip-ansi
Author: Ewen Le Bihan
Author-email: ewen.lebihan7@gmail.com
Requires-Python: >=3.8,<4.0
Classifier: Programming Language :: Python :: 3
Classifier: Programming Language :: Python :: 3.8
Project-URL: Repository, https://github.com/ewen-lbh/python-strip-ansi
